.travis.yml
AUTHORS
ChangeLog
LICENSE
README.rst
log.txt
requirements.txt
setup.cfg
setup.py
test-requirements.txt
tox.ini
doc/Makefile
doc/conf.py
doc/index.rst
doc/make.bat
jenkins_job_builder_workflow.egg-info/PKG-INFO
jenkins_job_builder_workflow.egg-info/SOURCES.txt
jenkins_job_builder_workflow.egg-info/dependency_links.txt
jenkins_job_builder_workflow.egg-info/entry_points.txt
jenkins_job_builder_workflow.egg-info/not-zip-safe
jenkins_job_builder_workflow.egg-info/pbr.json
jenkins_job_builder_workflow.egg-info/requires.txt
jenkins_job_builder_workflow.egg-info/top_level.txt
test/__init__.py
test/base.py
test/test_workflow.py
test/fixtures/project_workflow_001.xml
test/fixtures/project_workflow_001.yaml
test/fixtures/project_workflow_002.xml
test/fixtures/project_workflow_002.yaml
tools/release.bash
workflow_job/__init__.py
workflow_job/project_workflow.py