Metadata-Version: 1.0
Name: jenkins-job-builder-workflow
Version: 1.0.1
Summary: Workflow support for jenkins job builder.
Home-page: https://github.com/finnhaedicke/jenkins-job-builder-workflow
Author: Finn Haedicke
Author-email: finn_haedicke@gmx.net
License: Apache License, Version 2.0
Platform: UNKNOWN
